{
  "title": "舌の上の残像",
  "subtitle": "─ 辛味と人格のシミュラークル ─",
  "genre": "幻界ノベル",
  "date": "2026-03-23",
  "chars": {
    "narrator": { "name": "", "color": "#504060", "emoji": "" }
  },
  "scenario": [
    { "label": "standalone_start" },
    { "bg": "abyss" },
    { "speaker": "narrator", "expression": "", "text": "これは、「舌の上の残像」へ枝分かれした記録。\n辛味と人格のシミュラークル──残り香に気を取られた者が見る、偽の偽の世界。" },
    { "label": "entry_from_main" },
    { "bg": "abyss" },
    { "speaker": "narrator", "expression": "", "text": "食べ終わった。丼は空だ。でも口の中はまだ燃えている。\nいや、「燃えている」のだろうか？ カプサイシンは胃に流れた。舌の上にはもうカプサイシンはない。なのに、熱い。" },
    { "speaker": "narrator", "expression": "", "text": "これは記憶だ。受容体が覚えている。さっきまで送り続けていた「熱い」という信号の残響が、神経を反復している。実体のない信号。信号の残像。" },
    { "speaker": "narrator", "expression": "", "text": "目を閉じると、太陽の残像が見える。あれと同じだ。太陽はもう見ていないのに、網膜に焼きついた像が消えない。舌版の残像。" },
    { "speaker": "narrator", "expression": "", "text": "この残像は、偽の偽だ。カプサイシンが送った偽の火事信号の、さらに偽の反復。偽の二乗。\nでも、熱い。偽の二乗でも、感覚としては本物だ。" },
    { "speaker": "narrator", "expression": "", "text": "水を飲む。冷たい水が舌を通過する。一瞬だけ残像が薄れる。でもすぐに戻る。残像は消えない。消えるのを待つしかない。" },
    { "speaker": "narrator", "expression": "", "text": "消えるまでに、30分くらいかかるだろう。その間、舌は偽の残像を真実として報告し続ける。脳はそれを真実として処理し続ける。\n30分間の偽の真実。それは──30分間だけ存在する、もうひとつの現実だ。" },
    { "ending": { "title": "舌の上の残像", "subtitle": "偽の二乗でも、感覚としては本物だ。30分間だけ存在する、もうひとつの現実。" } }
  ]
}
